{
    "dataset_date": "10_2024",
    "dataset_page": "19",
    "dataset": [
        {
            "name": "Rey Von Crimson",
            "tag": "#GC1",
            "w": "25",
            "l": "20",
            "wr": "56",
            "elo": "diamond 2",
            "first_champ": "Lux",
            "second_champ": "Nami",
            "third_champ": "Karma",
            "incomplete": false
        },
        {
            "name": "TeXxmatei2",
            "tag": "#BR1",
            "w": "30",
            "l": "13",
            "wr": "70",
            "elo": "diamond 2",
            "first_champ": "Ezreal",
            "second_champ": "Kalista",
            "third_champ": "Lucian",
            "incomplete": false
        },
        {
            "name": "Slayer From Gods",
            "tag": "#BR1",
            "w": "43",
            "l": "43",
            "wr": "50",
            "elo": "diamond 2",
            "first_champ": "Jhin",
            "second_champ": "Kaisa",
            "third_champ": "Ezreal",
            "incomplete": false
        },
        {
            "name": "r\u00f8dz",
            "tag": "#frida",
            "w": "38",
            "l": "33",
            "wr": "54",
            "elo": "diamond 2",
            "first_champ": "Vayne",
            "second_champ": "Jinx",
            "third_champ": "Lucian",
            "incomplete": false
        },
        {
            "name": "Renato",
            "tag": "#BR1",
            "w": "24",
            "l": "17",
            "wr": "59",
            "elo": "diamond 2",
            "first_champ": "Fiora",
            "second_champ": "KSante",
            "third_champ": "Gwen",
            "incomplete": false
        },
        {
            "name": "Farrael",
            "tag": "#KBG",
            "w": "36",
            "l": "32",
            "wr": "53",
            "elo": "diamond 2",
            "first_champ": "Jhin",
            "second_champ": "Kaisa",
            "third_champ": "Caitlyn",
            "incomplete": false
        },
        {
            "name": "StormBomb",
            "tag": "#BOMBA",
            "w": "34",
            "l": "24",
            "wr": "59",
            "elo": "diamond 2",
            "first_champ": "Syndra",
            "second_champ": "AurelionSol",
            "third_champ": "Veigar",
            "incomplete": false
        },
        {
            "name": "Werpp",
            "tag": "#055",
            "w": "22",
            "l": "19",
            "wr": "54",
            "elo": "diamond 2",
            "first_champ": "Bard",
            "second_champ": "Rakan",
            "third_champ": "Poppy",
            "incomplete": false
        },
        {
            "name": "Scissoring",
            "tag": "#BR2",
            "w": "37",
            "l": "31",
            "wr": "54",
            "elo": "diamond 2",
            "first_champ": "Gwen",
            "second_champ": "Neeko",
            "third_champ": "Yone",
            "incomplete": false
        },
        {
            "name": "\u971c\u3055\u3093",
            "tag": "#LiSA",
            "w": "49",
            "l": "34",
            "wr": "59",
            "elo": "diamond 2",
            "first_champ": "Senna",
            "second_champ": "Lulu",
            "third_champ": "Smolder",
            "incomplete": false
        },
        {
            "name": "Hams",
            "tag": "#MAIN",
            "w": "27",
            "l": "21",
            "wr": "56",
            "elo": "diamond 2",
            "first_champ": "Gangplank",
            "second_champ": "Darius",
            "third_champ": "Jax",
            "incomplete": false
        },
        {
            "name": "wishing well",
            "tag": "#juice",
            "w": "79",
            "l": "73",
            "wr": "52",
            "elo": "diamond 2",
            "first_champ": "Zed",
            "second_champ": "Leblanc",
            "third_champ": "Ahri",
            "incomplete": false
        },
        {
            "name": "rhuan",
            "tag": "#zt69",
            "w": "18",
            "l": "7",
            "wr": "72",
            "elo": "diamond 2",
            "first_champ": "Katarina",
            "second_champ": "Zed",
            "third_champ": null,
            "incomplete": true
        },
        {
            "name": "chaewon fanboy",
            "tag": "#fear",
            "w": "17",
            "l": "10",
            "wr": "63",
            "elo": "diamond 2",
            "first_champ": "Nami",
            "second_champ": "Sona",
            "third_champ": "Senna",
            "incomplete": false
        },
        {
            "name": "Galas",
            "tag": "#157",
            "w": "18",
            "l": "12",
            "wr": "60",
            "elo": "diamond 2",
            "first_champ": "Jhin",
            "second_champ": "Kaisa",
            "third_champ": "Smolder",
            "incomplete": false
        },
        {
            "name": "Fugazy",
            "tag": "#Fugaz",
            "w": "29",
            "l": "18",
            "wr": "62",
            "elo": "diamond 2",
            "first_champ": "Jayce",
            "second_champ": "Smolder",
            "third_champ": "Udyr",
            "incomplete": false
        },
        {
            "name": "LM Ferzas",
            "tag": "#GRIND",
            "w": "20",
            "l": "21",
            "wr": "49",
            "elo": "diamond 2",
            "first_champ": "Elise",
            "second_champ": "LeeSin",
            "third_champ": "Viego",
            "incomplete": false
        },
        {
            "name": "Kagerume",
            "tag": "#BR1",
            "w": "11",
            "l": "2",
            "wr": "85",
            "elo": "diamond 2",
            "first_champ": "Jax",
            "second_champ": "Vladimir",
            "third_champ": "Shen",
            "incomplete": false
        },
        {
            "name": "mitsuuu1",
            "tag": "#777",
            "w": "34",
            "l": "32",
            "wr": "52",
            "elo": "diamond 2",
            "first_champ": "Kaisa",
            "second_champ": "Lucian",
            "third_champ": "Jhin",
            "incomplete": false
        },
        {
            "name": "anato",
            "tag": "#hxh",
            "w": "27",
            "l": "22",
            "wr": "55",
            "elo": "diamond 2",
            "first_champ": "Nidalee",
            "second_champ": "LeeSin",
            "third_champ": "Lillia",
            "incomplete": false
        },
        {
            "name": "xXGRXx Knight",
            "tag": "#BR1",
            "w": "18",
            "l": "12",
            "wr": "60",
            "elo": "diamond 2",
            "first_champ": "Annie",
            "second_champ": "Braum",
            "third_champ": null,
            "incomplete": true
        },
        {
            "name": "\ubca0\uc778 \ubca0\uc778 \ubca0\uc778",
            "tag": "#Vayne",
            "w": "22",
            "l": "15",
            "wr": "59",
            "elo": "diamond 2",
            "first_champ": "Kaisa",
            "second_champ": "Ezreal",
            "third_champ": "Vayne",
            "incomplete": false
        },
        {
            "name": "Nekron",
            "tag": "#Souls",
            "w": "25",
            "l": "18",
            "wr": "58",
            "elo": "diamond 2",
            "first_champ": "Yone",
            "second_champ": "Jax",
            "third_champ": "Riven",
            "incomplete": false
        },
        {
            "name": "insanojovem",
            "tag": "#GOD",
            "w": "19",
            "l": "13",
            "wr": "59",
            "elo": "diamond 2",
            "first_champ": "Zilean",
            "second_champ": "Zac",
            "third_champ": "Sylas",
            "incomplete": false
        },
        {
            "name": "pink killer",
            "tag": "#2745",
            "w": "22",
            "l": "19",
            "wr": "54",
            "elo": "diamond 2",
            "first_champ": "Jhin",
            "second_champ": "Ashe",
            "third_champ": "Varus",
            "incomplete": false
        },
        {
            "name": "Nagizin",
            "tag": "#XSQDL",
            "w": "62",
            "l": "60",
            "wr": "51",
            "elo": "diamond 2",
            "first_champ": "Jhin",
            "second_champ": "Ashe",
            "third_champ": "Ezreal",
            "incomplete": false
        },
        {
            "name": "Mia",
            "tag": "#miiau",
            "w": "28",
            "l": "22",
            "wr": "56",
            "elo": "diamond 2",
            "first_champ": "Nami",
            "second_champ": "Lulu",
            "third_champ": "Karma",
            "incomplete": false
        },
        {
            "name": "chihiro",
            "tag": "#image",
            "w": "55",
            "l": "52",
            "wr": "51",
            "elo": "diamond 2",
            "first_champ": "Yone",
            "second_champ": "Aurora",
            "third_champ": "Smolder",
            "incomplete": false
        },
        {
            "name": "\u7d2b\u8272\u306e\u77f3\u9e78",
            "tag": "#BR2",
            "w": "22",
            "l": "18",
            "wr": "55",
            "elo": "diamond 2",
            "first_champ": "Gragas",
            "second_champ": "Jayce",
            "third_champ": "Shen",
            "incomplete": false
        },
        {
            "name": "Flawless",
            "tag": "#Nino",
            "w": "20",
            "l": "12",
            "wr": "63",
            "elo": "diamond 2",
            "first_champ": "Yone",
            "second_champ": "Leblanc",
            "third_champ": "Jayce",
            "incomplete": false
        },
        {
            "name": "calma calabreso",
            "tag": "#meme",
            "w": "42",
            "l": "11",
            "wr": "79",
            "elo": "diamond 2",
            "first_champ": "Gwen",
            "second_champ": "Lillia",
            "third_champ": "Skarner",
            "incomplete": false
        },
        {
            "name": "Beanie",
            "tag": "#444",
            "w": "11",
            "l": "2",
            "wr": "85",
            "elo": "diamond 2",
            "first_champ": "Evelynn",
            "second_champ": "Graves",
            "third_champ": null,
            "incomplete": true
        },
        {
            "name": "escada rolante",
            "tag": "#BR1",
            "w": "11",
            "l": "6",
            "wr": "65",
            "elo": "diamond 2",
            "first_champ": "Rengar",
            "second_champ": "Orianna",
            "third_champ": "KogMaw",
            "incomplete": false
        },
        {
            "name": "NxtJhxnny",
            "tag": "#0001",
            "w": "22",
            "l": "14",
            "wr": "61",
            "elo": "diamond 2",
            "first_champ": "Akali",
            "second_champ": "Irelia",
            "third_champ": "Warwick",
            "incomplete": false
        },
        {
            "name": "joyboy",
            "tag": "#xxxxx",
            "w": "14",
            "l": "7",
            "wr": "67",
            "elo": "diamond 2",
            "first_champ": "Ekko",
            "second_champ": "LeeSin",
            "third_champ": "Nocturne",
            "incomplete": false
        },
        {
            "name": "Shadowheart",
            "tag": "#dani",
            "w": "37",
            "l": "25",
            "wr": "60",
            "elo": "diamond 2",
            "first_champ": "Lux",
            "second_champ": "Ahri",
            "third_champ": "Syndra",
            "incomplete": false
        },
        {
            "name": "Kaiser",
            "tag": "#Arts",
            "w": "21",
            "l": "18",
            "wr": "54",
            "elo": "diamond 2",
            "first_champ": "Poppy",
            "second_champ": "Aurora",
            "third_champ": "Jinx",
            "incomplete": false
        },
        {
            "name": "luizbazzo",
            "tag": "#BR1",
            "w": "23",
            "l": "20",
            "wr": "53",
            "elo": "diamond 2",
            "first_champ": "KogMaw",
            "second_champ": "Kaisa",
            "third_champ": "Ashe",
            "incomplete": false
        },
        {
            "name": "Blackerr",
            "tag": "#777",
            "w": "31",
            "l": "28",
            "wr": "53",
            "elo": "diamond 2",
            "first_champ": "Jax",
            "second_champ": "Fiora",
            "third_champ": "Camille",
            "incomplete": false
        },
        {
            "name": "pedro pyke",
            "tag": "#sesh",
            "w": "31",
            "l": "23",
            "wr": "57",
            "elo": "diamond 2",
            "first_champ": "Pyke",
            "second_champ": "Blitzcrank",
            "third_champ": "Swain",
            "incomplete": false
        },
        {
            "name": "Simbiozze",
            "tag": "#777",
            "w": "57",
            "l": "54",
            "wr": "51",
            "elo": "diamond 2",
            "first_champ": "Gwen",
            "second_champ": "Zyra",
            "third_champ": "Elise",
            "incomplete": false
        },
        {
            "name": "SANTOS FC 2011",
            "tag": "#Gavs",
            "w": "36",
            "l": "31",
            "wr": "54",
            "elo": "diamond 2",
            "first_champ": "Kindred",
            "second_champ": "XinZhao",
            "third_champ": "LeeSin",
            "incomplete": false
        },
        {
            "name": "HECARIM GAP",
            "tag": "#HECA",
            "w": "16",
            "l": "10",
            "wr": "62",
            "elo": "diamond 2",
            "first_champ": "Hecarim",
            "second_champ": "Malzahar",
            "third_champ": "Nocturne",
            "incomplete": false
        },
        {
            "name": "jOTA",
            "tag": "#ES27",
            "w": "59",
            "l": "62",
            "wr": "49",
            "elo": "diamond 2",
            "first_champ": "Lillia",
            "second_champ": "LeeSin",
            "third_champ": "Amumu",
            "incomplete": false
        },
        {
            "name": "LNG Zepty",
            "tag": "#fnx",
            "w": "12",
            "l": "5",
            "wr": "71",
            "elo": "diamond 2",
            "first_champ": "Rell",
            "second_champ": "Poppy",
            "third_champ": "Alistar",
            "incomplete": false
        },
        {
            "name": "Eu sou a Nami",
            "tag": "#BR1",
            "w": "48",
            "l": "32",
            "wr": "60",
            "elo": "diamond 2",
            "first_champ": "Nami",
            "second_champ": "Lulu",
            "third_champ": "Soraka",
            "incomplete": false
        },
        {
            "name": "q\u00edcheren",
            "tag": "#BR1",
            "w": "48",
            "l": "24",
            "wr": "67",
            "elo": "diamond 2",
            "first_champ": "Camille",
            "second_champ": "Kayle",
            "third_champ": "TahmKench",
            "incomplete": false
        },
        {
            "name": "DarkWolf",
            "tag": "#21062",
            "w": "32",
            "l": "26",
            "wr": "55",
            "elo": "diamond 2",
            "first_champ": "Anivia",
            "second_champ": "Camille",
            "third_champ": "Viktor",
            "incomplete": false
        },
        {
            "name": "THANATOSSSSSSS",
            "tag": "#BR777",
            "w": "25",
            "l": "25",
            "wr": "50",
            "elo": "diamond 2",
            "first_champ": "Yone",
            "second_champ": "Lissandra",
            "third_champ": "Xerath",
            "incomplete": false
        },
        {
            "name": "Fernanda Bolos",
            "tag": "#Ahri",
            "w": "12",
            "l": "7",
            "wr": "63",
            "elo": "diamond 2",
            "first_champ": "Ahri",
            "second_champ": "Nami",
            "third_champ": "Karma",
            "incomplete": false
        },
        {
            "name": "FenTrel",
            "tag": "#\u0414\u0435\u043c\u043e\u043d",
            "w": "24",
            "l": "17",
            "wr": "59",
            "elo": "diamond 2",
            "first_champ": "Trundle",
            "second_champ": "Fiora",
            "third_champ": "Mordekaiser",
            "incomplete": false
        },
        {
            "name": "Let me C0OK v9",
            "tag": "#BR1",
            "w": "36",
            "l": "32",
            "wr": "53",
            "elo": "diamond 2",
            "first_champ": "LeeSin",
            "second_champ": "Lucian",
            "third_champ": "Yasuo",
            "incomplete": false
        },
        {
            "name": "Ziu",
            "tag": "#000",
            "w": "25",
            "l": "19",
            "wr": "57",
            "elo": "diamond 2",
            "first_champ": "Tristana",
            "second_champ": "Velkoz",
            "third_champ": "Ezreal",
            "incomplete": false
        },
        {
            "name": "Lausso",
            "tag": "#001",
            "w": "24",
            "l": "16",
            "wr": "60",
            "elo": "diamond 2",
            "first_champ": "Illaoi",
            "second_champ": "Kled",
            "third_champ": null,
            "incomplete": true
        },
        {
            "name": "Nakataojj",
            "tag": "#BR1",
            "w": "15",
            "l": "8",
            "wr": "65",
            "elo": "diamond 2",
            "first_champ": "Sona",
            "second_champ": null,
            "third_champ": null,
            "incomplete": true
        },
        {
            "name": "Dibs",
            "tag": "#BR1",
            "w": "35",
            "l": "27",
            "wr": "56",
            "elo": "diamond 2",
            "first_champ": "TahmKench",
            "second_champ": "Kayle",
            "third_champ": "Jax",
            "incomplete": false
        },
        {
            "name": "temp637444333",
            "tag": "#BR1",
            "w": "14",
            "l": "9",
            "wr": "61",
            "elo": "diamond 2",
            "first_champ": "Kassadin",
            "second_champ": "Karthus",
            "third_champ": "Fiora",
            "incomplete": false
        },
        {
            "name": "Percedal",
            "tag": "#demon",
            "w": "22",
            "l": "14",
            "wr": "61",
            "elo": "diamond 2",
            "first_champ": "Volibear",
            "second_champ": "Khazix",
            "third_champ": "Gnar",
            "incomplete": false
        },
        {
            "name": "MaxoEscrotor",
            "tag": "#666",
            "w": "55",
            "l": "54",
            "wr": "50",
            "elo": "diamond 2",
            "first_champ": "Evelynn",
            "second_champ": "Viego",
            "third_champ": null,
            "incomplete": true
        },
        {
            "name": "TiranoSauloRex",
            "tag": "#REX",
            "w": "40",
            "l": "36",
            "wr": "53",
            "elo": "diamond 2",
            "first_champ": "Nocturne",
            "second_champ": "Tristana",
            "third_champ": "Rammus",
            "incomplete": false
        },
        {
            "name": "miLt",
            "tag": "#6969",
            "w": "30",
            "l": "28",
            "wr": "52",
            "elo": "diamond 2",
            "first_champ": "MasterYi",
            "second_champ": "Belveth",
            "third_champ": "Lulu",
            "incomplete": false
        },
        {
            "name": "L\u00d8CK",
            "tag": "#n\u00ba 4",
            "w": "24",
            "l": "21",
            "wr": "53",
            "elo": "diamond 2",
            "first_champ": "Jhin",
            "second_champ": "Lucian",
            "third_champ": "Ezreal",
            "incomplete": false
        },
        {
            "name": "Flash",
            "tag": "#FLU",
            "w": "42",
            "l": "39",
            "wr": "52",
            "elo": "diamond 2",
            "first_champ": "Syndra",
            "second_champ": "Aurora",
            "third_champ": "Yone",
            "incomplete": false
        },
        {
            "name": "King Aomine",
            "tag": "#BR1",
            "w": "35",
            "l": "30",
            "wr": "54",
            "elo": "diamond 2",
            "first_champ": "Zac",
            "second_champ": "Shen",
            "third_champ": "Gnar",
            "incomplete": false
        },
        {
            "name": "cachorrodomato",
            "tag": "#D0307",
            "w": "27",
            "l": "19",
            "wr": "59",
            "elo": "diamond 2",
            "first_champ": "LeeSin",
            "second_champ": "Yasuo",
            "third_champ": "Nidalee",
            "incomplete": false
        },
        {
            "name": "Vinny",
            "tag": "#vini",
            "w": "23",
            "l": "17",
            "wr": "57",
            "elo": "diamond 2",
            "first_champ": null,
            "second_champ": null,
            "third_champ": null,
            "incomplete": true
        },
        {
            "name": "B0AT",
            "tag": "#BR1",
            "w": "27",
            "l": "24",
            "wr": "53",
            "elo": "diamond 2",
            "first_champ": "Lucian",
            "second_champ": "Gnar",
            "third_champ": "Jhin",
            "incomplete": false
        },
        {
            "name": "SoLoBr",
            "tag": "#BR2",
            "w": "37",
            "l": "33",
            "wr": "53",
            "elo": "diamond 2",
            "first_champ": "Yone",
            "second_champ": "Viego",
            "third_champ": "Sylas",
            "incomplete": false
        },
        {
            "name": "just r\u00e4y",
            "tag": "#BR1",
            "w": "25",
            "l": "19",
            "wr": "57",
            "elo": "diamond 2",
            "first_champ": "Lucian",
            "second_champ": "Jhin",
            "third_champ": "Kalista",
            "incomplete": false
        },
        {
            "name": "negue",
            "tag": "#bento",
            "w": "15",
            "l": "6",
            "wr": "71",
            "elo": "diamond 2",
            "first_champ": "Kayn",
            "second_champ": "MasterYi",
            "third_champ": "Hecarim",
            "incomplete": false
        },
        {
            "name": "Namicita",
            "tag": "#RULO",
            "w": "21",
            "l": "15",
            "wr": "58",
            "elo": "diamond 2",
            "first_champ": "Nami",
            "second_champ": "Syndra",
            "third_champ": "Nidalee",
            "incomplete": false
        },
        {
            "name": "Koenigsegg",
            "tag": "#GH0ST",
            "w": "19",
            "l": "12",
            "wr": "61",
            "elo": "diamond 2",
            "first_champ": "KogMaw",
            "second_champ": "Jhin",
            "third_champ": "Caitlyn",
            "incomplete": false
        },
        {
            "name": "ouch",
            "tag": "#yse",
            "w": "11",
            "l": "6",
            "wr": "65",
            "elo": "diamond 2",
            "first_champ": "Yasuo",
            "second_champ": "Zed",
            "third_champ": "Renekton",
            "incomplete": false
        },
        {
            "name": "flp z B",
            "tag": "#kng",
            "w": "49",
            "l": "38",
            "wr": "56",
            "elo": "diamond 2",
            "first_champ": "Yone",
            "second_champ": "Smolder",
            "third_champ": "Sylas",
            "incomplete": false
        },
        {
            "name": "Princesa",
            "tag": "#Sona",
            "w": "33",
            "l": "35",
            "wr": "49",
            "elo": "diamond 2",
            "first_champ": "Kindred",
            "second_champ": "Renata",
            "third_champ": "Graves",
            "incomplete": false
        },
        {
            "name": "Jipgeria",
            "tag": "#DWG",
            "w": "19",
            "l": "11",
            "wr": "63",
            "elo": "diamond 2",
            "first_champ": "Camille",
            "second_champ": "Yone",
            "third_champ": "Kaisa",
            "incomplete": false
        },
        {
            "name": "Fizzica Qu\u00e2ntica",
            "tag": "#BR1",
            "w": "14",
            "l": "6",
            "wr": "70",
            "elo": "diamond 2",
            "first_champ": "Hwei",
            "second_champ": "Jhin",
            "third_champ": "Smolder",
            "incomplete": false
        },
        {
            "name": "Blad",
            "tag": "#000",
            "w": "30",
            "l": "23",
            "wr": "57",
            "elo": "diamond 2",
            "first_champ": "Thresh",
            "second_champ": "Nautilus",
            "third_champ": "Lissandra",
            "incomplete": false
        },
        {
            "name": "amish",
            "tag": "#giri",
            "w": "91",
            "l": "87",
            "wr": "51",
            "elo": "diamond 2",
            "first_champ": "Ahri",
            "second_champ": "Katarina",
            "third_champ": "Anivia",
            "incomplete": false
        },
        {
            "name": "BIXO DA UFABC",
            "tag": "#BR1",
            "w": "12",
            "l": "2",
            "wr": "86",
            "elo": "diamond 2",
            "first_champ": "Darius",
            "second_champ": "Volibear",
            "third_champ": "Olaf",
            "incomplete": false
        },
        {
            "name": "dedezin kit bota",
            "tag": "#IVERN",
            "w": "22",
            "l": "18",
            "wr": "55",
            "elo": "diamond 2",
            "first_champ": "Pyke",
            "second_champ": "Qiyana",
            "third_champ": "Ivern",
            "incomplete": false
        },
        {
            "name": "Amo doidas",
            "tag": "#TDH",
            "w": "25",
            "l": "19",
            "wr": "57",
            "elo": "diamond 2",
            "first_champ": null,
            "second_champ": null,
            "third_champ": null,
            "incomplete": true
        },
        {
            "name": "no one is pure",
            "tag": "#migo",
            "w": "34",
            "l": "32",
            "wr": "52",
            "elo": "diamond 2",
            "first_champ": "Jinx",
            "second_champ": "Nautilus",
            "third_champ": "Braum",
            "incomplete": false
        },
        {
            "name": "Deathcore",
            "tag": "#BR1",
            "w": "72",
            "l": "44",
            "wr": "62",
            "elo": "diamond 2",
            "first_champ": "Kaisa",
            "second_champ": "Vayne",
            "third_champ": "Jinx",
            "incomplete": false
        },
        {
            "name": "Dudu MC",
            "tag": "#BR1",
            "w": "26",
            "l": "21",
            "wr": "55",
            "elo": "diamond 2",
            "first_champ": "Lucian",
            "second_champ": "Karthus",
            "third_champ": "Ezreal",
            "incomplete": false
        },
        {
            "name": "despairful",
            "tag": "#mat",
            "w": "43",
            "l": "39",
            "wr": "52",
            "elo": "diamond 2",
            "first_champ": "Kayn",
            "second_champ": "Talon",
            "third_champ": "Viego",
            "incomplete": false
        },
        {
            "name": "ohmwrecker",
            "tag": "#brc",
            "w": "24",
            "l": "19",
            "wr": "56",
            "elo": "diamond 2",
            "first_champ": "JarvanIV",
            "second_champ": null,
            "third_champ": null,
            "incomplete": true
        },
        {
            "name": "CRD Starkky",
            "tag": "#8080",
            "w": "12",
            "l": "4",
            "wr": "75",
            "elo": "diamond 2",
            "first_champ": "Jax",
            "second_champ": "KSante",
            "third_champ": "Renekton",
            "incomplete": false
        },
        {
            "name": "Ruler",
            "tag": "#prime",
            "w": "26",
            "l": "22",
            "wr": "54",
            "elo": "diamond 2",
            "first_champ": "Kaisa",
            "second_champ": "Jinx",
            "third_champ": "Kalista",
            "incomplete": false
        },
        {
            "name": "True Change",
            "tag": "#Hope",
            "w": "16",
            "l": "9",
            "wr": "64",
            "elo": "diamond 2",
            "first_champ": "Riven",
            "second_champ": "Yone",
            "third_champ": "Kayn",
            "incomplete": false
        },
        {
            "name": "suggar bunny",
            "tag": "#BR1",
            "w": "39",
            "l": "49",
            "wr": "44",
            "elo": "diamond 2",
            "first_champ": "Morgana",
            "second_champ": "Lulu",
            "third_champ": "Nami",
            "incomplete": false
        },
        {
            "name": "fades",
            "tag": "#gwen",
            "w": "43",
            "l": "42",
            "wr": "51",
            "elo": "diamond 2",
            "first_champ": "Rell",
            "second_champ": "Alistar",
            "third_champ": "Rakan",
            "incomplete": false
        },
        {
            "name": "javalava",
            "tag": "#BR1",
            "w": "83",
            "l": "73",
            "wr": "53",
            "elo": "diamond 2",
            "first_champ": "Viego",
            "second_champ": "Mordekaiser",
            "third_champ": "Gragas",
            "incomplete": false
        },
        {
            "name": "fire",
            "tag": "#SWE",
            "w": "28",
            "l": "26",
            "wr": "52",
            "elo": "diamond 2",
            "first_champ": "JarvanIV",
            "second_champ": "XinZhao",
            "third_champ": "LeeSin",
            "incomplete": false
        },
        {
            "name": "ClaudiaArraiia",
            "tag": "#1211",
            "w": "37",
            "l": "37",
            "wr": "50",
            "elo": "diamond 2",
            "first_champ": "Belveth",
            "second_champ": "Karthus",
            "third_champ": "Maokai",
            "incomplete": false
        },
        {
            "name": "Megalovania",
            "tag": "#BR1",
            "w": "33",
            "l": "28",
            "wr": "54",
            "elo": "diamond 2",
            "first_champ": "Swain",
            "second_champ": "Orianna",
            "third_champ": "Pantheon",
            "incomplete": false
        },
        {
            "name": "krono",
            "tag": "#CN1",
            "w": "13",
            "l": "11",
            "wr": "54",
            "elo": "diamond 2",
            "first_champ": "Aphelios",
            "second_champ": "Lucian",
            "third_champ": "Sivir",
            "incomplete": false
        },
        {
            "name": "Lukz1nNn \u30b7",
            "tag": "#Lucas",
            "w": "24",
            "l": "19",
            "wr": "56",
            "elo": "diamond 2",
            "first_champ": "Syndra",
            "second_champ": "Kaisa",
            "third_champ": "Smolder",
            "incomplete": false
        },
        {
            "name": "Lisan Al Gaib",
            "tag": "#MIND",
            "w": "55",
            "l": "51",
            "wr": "52",
            "elo": "diamond 2",
            "first_champ": "Lucian",
            "second_champ": "Jax",
            "third_champ": "Xerath",
            "incomplete": false
        },
        {
            "name": "larama",
            "tag": "#190",
            "w": "47",
            "l": "33",
            "wr": "59",
            "elo": "diamond 2",
            "first_champ": "Akali",
            "second_champ": "TwistedFate",
            "third_champ": "Smolder",
            "incomplete": false
        }
    ]
}